{
  "kind": "spec_vs_diff_report",
  "version": "1.0",
  "generatedAt": "2026-02-24T20:00:16.323Z",
  "summary": "Both REQ-1 and REQ-2 are implemented in the diff. Header.tsx sets the logo src to '/assets/generated/deeds-logo.png', and Gate.tsx also sets the hero logo src to '/assets/generated/deeds-logo.png'. LoginPrompt.tsx uses the same asset via the StarEffectLogo wrapper component. No missing requirements or hallucinated features were identified.",
  "missing_requirements": [],
  "hallucinated_features": [],
  "confidence": 0.95,
  "changed_files": [
    "frontend-file-summaries.txt",
    "frontend/src/components/Gate.tsx",
    "frontend/src/components/Header.tsx",
    "frontend/src/components/LoginPrompt.tsx",
    "project_state.json"
  ]
}